2-Kronecker_d2/2-No optimization/RTL/register.v
module Register #(parameter N = 1)(in, clk, out);
    input [N-1 : 0] in;
    input clk;
    output reg [N-1 : 0] out;

    always @ (posedge clk) begin
        out <= in;
    end

endmodule

2-Kronecker_d2/2-No optimization/RTL/DOM_d2.v

module and_dom_indep_d2 (clk, x, y, r, z);

    input clk;
    input[2:0] x, y;
    input[2:0] r;
    output [2:0] z;

    wire AND1, AND2, AND3, 
         AND4, AND5, AND6, 
         AND7, AND8, AND9;
    wire [9:1] DFFout;
    wire r0XORAND2, r1XORAND3,
         r0XORAND4, r2XORAND6,
         r1XORAND7, r2XORAND8;

    assign AND1 = x[0] & y[0];
    assign AND2 = x[0] & y[1];
    assign AND3 = x[0] & y[2];
    assign r0XORAND2 = r[0] ^ AND2;
    assign r1XORAND3 = r[1] ^ AND3;
    Register #(1) D1 (AND1,      clk, DFFout[1]);
    Register #(1) D2 (r0XORAND2, clk, DFFout[2]);
    Register #(1) D3 (r1XORAND3, clk, DFFout[3]);
    assign z[0] = DFFout[1] ^ DFFout[2] ^ DFFout[3];

    assign AND4 = x[1] & y[0];
    assign AND5 = x[1] & y[1];
    assign AND6 = x[1] & y[2];
    assign r0XORAND4 = r[0] ^ AND4;
    assign r2XORAND6 = r[2] ^ AND6;
    Register #(1) D4 (r0XORAND4, clk, DFFout[4]);
    Register #(1) D5 (AND5,      clk, DFFout[5]);
    Register #(1) D6 (r2XORAND6, clk, DFFout[6]);
    assign z[1] = DFFout[4] ^ DFFout[5] ^ DFFout[6];

    assign AND7 = x[2] & y[0];
    assign AND8 = x[2] & y[1];
    assign AND9 = x[2] & y[2];
    assign r1XORAND7 = r[1] ^ AND7;
    assign r2XORAND8 = r[2] ^ AND8;
    Register #(1) D7 (r1XORAND7, clk, DFFout[7]);
    Register #(1) D8 (r2XORAND8, clk, DFFout[8]);
    Register #(1) D9 (AND9,      clk, DFFout[9]);
    assign z[2] = DFFout[7] ^ DFFout[8] ^ DFFout[9];

endmodule

Kronecker_d2/HDL_codes/kronecker_d2.v
module kronecker_d2 (clk, shared_inp, PRNG, out);
    
    input clk;
    input [12:0] PRNG;
    input [23 : 0] shared_inp;
    output [2:0] out;

    wire [2 : 0] w1, w2, w3, w4, w5, w6,
    r1, r2, r3, r4, r5, r6, r7,
    Ax0, Ax1, Ax2, Ax3,
    Ay0, Ay1, Ay2, Ay3;

    assign r1 = PRNG[2:0];
    assign r2 = PRNG[5:3];
    assign r3 = PRNG[8:6];
    assign r4 = PRNG[11:9];
    assign r5[0] = r3[0];
    assign r5[1] = r4[1];
    assign r6[0] = r1[0];
    assign r6[1] = r2[1];
    assign r7[2] = PRNG[12];  

    Register #(1) for_r52 ((r3[2] ^ r4[2]), clk, r5[2]);
    Register #(1) for_r62 ((r1[2] ^ r2[2]), clk, r6[2]);
    Register #(1) for_r70 ((r2[0] ^ r4[0]), clk, r7[1]);
    Register #(1) for_r71 ((r1[1] ^ r3[1]), clk, r7[0]);

    assign Ax0 = {shared_inp[0], shared_inp[8],  ~shared_inp[16]};
    assign Ay0 = {shared_inp[1], shared_inp[9],  ~shared_inp[17]};
    assign Ax1 = {shared_inp[2], shared_inp[10], ~shared_inp[18]};
    assign Ay1 = {shared_inp[3], shared_inp[11], ~shared_inp[19]};
    assign Ax2 = {shared_inp[4], shared_inp[12], ~shared_inp[20]};
    assign Ay2 = {shared_inp[5], shared_inp[13], ~shared_inp[21]};
    assign Ax3 = {shared_inp[6], shared_inp[14], ~shared_inp[22]};
    assign Ay3 = {shared_inp[7], shared_inp[15], ~shared_inp[23]};
    
    and_dom_indep_d2 G1 (clk, Ax0, Ay0, r1, w1);
    and_dom_indep_d2 G2 (clk, Ax1, Ay1, r2, w2);
    and_dom_indep_d2 G3 (clk, Ax2, Ay2, r3, w3);
    and_dom_indep_d2 G4 (clk, Ax3, Ay3, r4, w4);
    and_dom_indep_d2 G5 (clk, w1, w2, r5, w5);
    and_dom_indep_d2 G6 (clk, w3, w4, r6, w6);
    and_dom_indep_d2 G7 (clk, w5, w6, r7, out);

endmodule

Kronecker_d2/HDL_codes/TB_kron.v
`timescale 1ns / 1ps

module TB_kronecker ();
    reg clk;
    reg [12:0] rnd;
    reg [23 : 0] shared_inp; 
    wire [2:0] out;
     
    kronecker_d2 UUT (clk, shared_inp, rnd, out);

    always #5 clk = ~clk;
    always #10 rnd = $random;
    
    reg [7:0] share0, share1, val;

    initial begin
        $dumpfile("kron.vcd");
        $dumpvars(0, TB_kronecker);
        clk = 0;
        rnd = $random;
        
        shared_inp = 24'h25A347; #10;

        share0 = $random; share1 = $random; val = 8'b0 ^ share0 ^ share1;
        shared_inp = {val, share0, share1};
        #10;
        repeat (4)  begin 
            shared_inp = $random; #10;
        end
        share0 = $random; share1 = $random; val = 8'b0 ^ share0 ^ share1;
        shared_inp = {val, share0, share1}; #10;
        repeat (5)  begin 
            shared_inp = $random; #10;
        end
        #60;
        $finish;

    end
    
    wire OUT_unshared;
    wire [7:0] INP_unshared;
    assign OUT_unshared = out[0] ^ out[1] ^ out[2];
    assign INP_unshared = shared_inp[7:0] ^ shared_inp[15:8] ^ shared_inp[23:16];

endmodule

Kronecker_d2/HDL_codes/kron.vcd
$date
	Sat Feb  1 13:54:03 2025
$end
$version
	Icarus Verilog
$end
$timescale
	1ps
$end
$scope module TB_kronecker $end
$var wire 8 ! INP_unshared [7:0] $end
$var wire 1 " OUT_unshared $end
$var wire 3 # out [2:0] $end
$var reg 1 $ clk $end
$var reg 13 % rnd [12:0] $end
$var reg 8 & share0 [7:0] $end
$var reg 8 ' share1 [7:0] $end
$var reg 24 ( shared_inp [23:0] $end
$var reg 8 ) val [7:0] $end
$scope module UUT $end
$var wire 13 * PRNG [12:0] $end
$var wire 1 $ clk $end
$var wire 24 + shared_inp [23:0] $end
$var wire 3 , w6 [2:0] $end
$var wire 3 - w5 [2:0] $end
$var wire 3 . w4 [2:0] $end
$var wire 3 / w3 [2:0] $end
$var wire 3 0 w2 [2:0] $end
$var wire 3 1 w1 [2:0] $end
$var wire 3 2 r7 [2:0] $end
$var wire 3 3 r6 [2:0] $end
$var wire 3 4 r5 [2:0] $end
$var wire 3 5 r4 [2:0] $end
$var wire 3 6 r3 [2:0] $end
$var wire 3 7 r2 [2:0] $end
$var wire 3 8 r1 [2:0] $end
$var wire 3 9 out [2:0] $end
$var wire 3 : Ay3 [2:0] $end
$var wire 3 ; Ay2 [2:0] $end
$var wire 3 < Ay1 [2:0] $end
$var wire 3 = Ay0 [2:0] $end
$var wire 3 > Ax3 [2:0] $end
$var wire 3 ? Ax2 [2:0] $end
$var wire 3 @ Ax1 [2:0] $end
$var wire 3 A Ax0 [2:0] $end
$scope module G1 $end
$var wire 1 B AND1 $end
$var wire 1 C AND2 $end
$var wire 1 D AND3 $end
$var wire 1 E AND4 $end
$var wire 1 F AND5 $end
$var wire 1 G AND6 $end
$var wire 1 H AND7 $end
$var wire 1 I AND8 $end
$var wire 1 J AND9 $end
$var wire 1 $ clk $end
$var wire 3 K r [2:0] $end
$var wire 1 L r0XORAND2 $end
$var wire 1 M r0XORAND4 $end
$var wire 1 N r1XORAND3 $end
$var wire 1 O r1XORAND7 $end
$var wire 1 P r2XORAND6 $end
$var wire 1 Q r2XORAND8 $end
$var wire 3 R x [2:0] $end
$var wire 3 S y [2:0] $end
$var wire 3 T z [2:0] $end
$var wire 9 U DFFout [9:1] $end
$scope module D1 $end
$var wire 1 $ clk $end
$var wire 1 B in $end
$var parameter 32 V N $end
$var reg 1 W out $end
$upscope $end
$scope module D2 $end
$var wire 1 $ clk $end
$var wire 1 L in $end
$var parameter 32 X N $end
$var reg 1 Y out $end
$upscope $end
$scope module D3 $end
$var wire 1 $ clk $end
$var wire 1 N in $end
$var parameter 32 Z N $end
$var reg 1 [ out $end
$upscope $end
$scope module D4 $end
$var wire 1 $ clk $end
$var wire 1 M in $end
$var parameter 32 \ N $end
$var reg 1 ] out $end
$upscope $end
$scope module D5 $end
$var wire 1 $ clk $end
$var wire 1 F in $end
$var parameter 32 ^ N $end
$var reg 1 _ out $end
$upscope $end
$scope module D6 $end
$var wire 1 $ clk $end
$var wire 1 P in $end
$var parameter 32 ` N $end
$var reg 1 a out $end
$upscope $end
$scope module D7 $end
$var wire 1 $ clk $end
$var wire 1 O in $end
$var parameter 32 b N $end
$var reg 1 c out $end
$upscope $end
$scope module D8 $end
$var wire 1 $ clk $end
$var wire 1 Q in $end
$var parameter 32 d N $end
$var reg 1 e out $end
$upscope $end
$scope module D9 $end
$var wire 1 $ clk $end
$var wire 1 J in $end
$var parameter 32 f N $end
$var reg 1 g out $end
$upscope $end
$upscope $end
$scope module G2 $end
$var wire 1 h AND1 $end
$var wire 1 i AND2 $end
$var wire 1 j AND3 $end
$var wire 1 k AND4 $end
$var wire 1 l AND5 $end
$var wire 1 m AND6 $end
$var wire 1 n AND7 $end
$var wire 1 o AND8 $end
$var wire 1 p AND9 $end
$var wire 1 $ clk $end
$var wire 3 q r [2:0] $end
$var wire 1 r r0XORAND2 $end
$var wire 1 s r0XORAND4 $end
$var wire 1 t r1XORAND3 $end
$var wire 1 u r1XORAND7 $end
$var wire 1 v r2XORAND6 $end
$var wire 1 w r2XORAND8 $end
$var wire 3 x x [2:0] $end
$var wire 3 y y [2:0] $end
$var wire 3 z z [2:0] $end
$var wire 9 { DFFout [9:1] $end
$scope module D1 $end
$var wire 1 $ clk $end
$var wire 1 h in $end
$var parameter 32 | N $end
$var reg 1 } out $end
$upscope $end
$scope module D2 $end
$var wire 1 $ clk $end
$var wire 1 r in $end
$var parameter 32 ~ N $end
$var reg 1 !" out $end
$upscope $end
$scope module D3 $end
$var wire 1 $ clk $end
$var wire 1 t in $end
$var parameter 32 "" N $end
$var reg 1 #" out $end
$upscope $end
$scope module D4 $end
$var wire 1 $ clk $end
$var wire 1 s in $end
$var parameter 32 $" N $end
$var reg 1 %" out $end
$upscope $end
$scope module D5 $end
$var wire 1 $ clk $end
$var wire 1 l in $end
$var parameter 32 &" N $end
$var reg 1 '" out $end
$upscope $end
$scope module D6 $end
$var wire 1 $ clk $end
$var wire 1 v in $end
$var parameter 32 (" N $end
$var reg 1 )" out $end
$upscope $end
$scope module D7 $end
$var wire 1 $ clk $end
$var wire 1 u in $end
$var parameter 32 *" N $end
$var reg 1 +" out $end
$upscope $end
$scope module D8 $end
$var wire 1 $ clk $end
$var wire 1 w in $end
$var parameter 32 ," N $end
$var reg 1 -" out $end
$upscope $end
$scope module D9 $end
$var wire 1 $ clk $end
$var wire 1 p in $end
$var parameter 32 ." N $end
$var reg 1 /" out $end
$upscope $end
$upscope $end
$scope module G3 $end
$var wire 1 0" AND1 $end
$var wire 1 1" AND2 $end
$var wire 1 2" AND3 $end
$var wire 1 3" AND4 $end
$var wire 1 4" AND5 $end
$var wire 1 5" AND6 $end
$var wire 1 6" AND7 $end
$var wire 1 7" AND8 $end
$var wire 1 8" AND9 $end
$var wire 1 $ clk $end
$var wire 3 9" r [2:0] $end
$var wire 1 :" r0XORAND2 $end
$var wire 1 ;" r0XORAND4 $end
$var wire 1 <" r1XORAND3 $end
$var wire 1 =" r1XORAND7 $end
$var wire 1 >" r2XORAND6 $end
$var wire 1 ?" r2XORAND8 $end
$var wire 3 @" x [2:0] $end
$var wire 3 A" y [2:0] $end
$var wire 3 B" z [2:0] $end
$var wire 9 C" DFFout [9:1] $end
$scope module D1 $end
$var wire 1 $ clk $end
$var wire 1 0" in $end
$var parameter 32 D" N $end
$var reg 1 E" out $end
$upscope $end
$scope module D2 $end
$var wire 1 $ clk $end
$var wire 1 :" in $end
$var parameter 32 F" N $end
$var reg 1 G" out $end
$upscope $end
$scope module D3 $end
$var wire 1 $ clk $end
$var wire 1 <" in $end
$var parameter 32 H" N $end
$var reg 1 I" out $end
$upscope $end
$scope module D4 $end
$var wire 1 $ clk $end
$var wire 1 ;" in $end
$var parameter 32 J" N $end
$var reg 1 K" out $end
$upscope $end
$scope module D5 $end
$var wire 1 $ clk $end
$var wire 1 4" in $end
$var parameter 32 L" N $end
$var reg 1 M" out $end
$upscope $end
$scope module D6 $end
$var wire 1 $ clk $end
$var wire 1 >" in $end
$var parameter 32 N" N $end
$var reg 1 O" out $end
$upscope $end
$scope module D7 $end
$var wire 1 $ clk $end
$var wire 1 =" in $end
$var parameter 32 P" N $end
$var reg 1 Q" out $end
$upscope $end
$scope module D8 $end
$var wire 1 $ clk $end
$var wire 1 ?" in $end
$var parameter 32 R" N $end
$var reg 1 S" out $end
$upscope $end
$scope module D9 $end
$var wire 1 $ clk $end
$var wire 1 8" in $end
$var parameter 32 T" N $end
$var reg 1 U" out $end
$upscope $end
$upscope $end
$scope module G4 $end
$var wire 1 V" AND1 $end
$var wire 1 W" AND2 $end
$var wire 1 X" AND3 $end
$var wire 1 Y" AND4 $end
$var wire 1 Z" AND5 $end
$var wire 1 [" AND6 $end
$var wire 1 \" AND7 $end
$var wire 1 ]" AND8 $end
$var wire 1 ^" AND9 $end
$var wire 1 $ clk $end
$var wire 3 _" r [2:0] $end
$var wire 1 `" r0XORAND2 $end
$var wire 1 a" r0XORAND4 $end
$var wire 1 b" r1XORAND3 $end
$var wire 1 c" r1XORAND7 $end
$var wire 1 d" r2XORAND6 $end
$var wire 1 e" r2XORAND8 $end
$var wire 3 f" x [2:0] $end
$var wire 3 g" y [2:0] $end
$var wire 3 h" z [2:0] $end
$var wire 9 i" DFFout [9:1] $end
$scope module D1 $end
$var wire 1 $ clk $end
$var wire 1 V" in $end
$var parameter 32 j" N $end
$var reg 1 k" out $end
$upscope $end
$scope module D2 $end
$var wire 1 $ clk $end
$var wire 1 `" in $end
$var parameter 32 l" N $end
$var reg 1 m" out $end
$upscope $end
$scope module D3 $end
$var wire 1 $ clk $end
$var wire 1 b" in $end
$var parameter 32 n" N $end
$var reg 1 o" out $end
$upscope $end
$scope module D4 $end
$var wire 1 $ clk $end
$var wire 1 a" in $end
$var parameter 32 p" N $end
$var reg 1 q" out $end
$upscope $end
$scope module D5 $end
$var wire 1 $ clk $end
$var wire 1 Z" in $end
$var parameter 32 r" N $end
$var reg 1 s" out $end
$upscope $end
$scope module D6 $end
$var wire 1 $ clk $end
$var wire 1 d" in $end
$var parameter 32 t" N $end
$var reg 1 u" out $end
$upscope $end
$scope module D7 $end
$var wire 1 $ clk $end
$var wire 1 c" in $end
$var parameter 32 v" N $end
$var reg 1 w" out $end
$upscope $end
$scope module D8 $end
$var wire 1 $ clk $end
$var wire 1 e" in $end
$var parameter 32 x" N $end
$var reg 1 y" out $end
$upscope $end
$scope module D9 $end
$var wire 1 $ clk $end
$var wire 1 ^" in $end
$var parameter 32 z" N $end
$var reg 1 {" out $end
$upscope $end
$upscope $end
$scope module G5 $end
$var wire 1 |" AND1 $end
$var wire 1 }" AND2 $end
$var wire 1 ~" AND3 $end
$var wire 1 !# AND4 $end
$var wire 1 "# AND5 $end
$var wire 1 ## AND6 $end
$var wire 1 $# AND7 $end
$var wire 1 %# AND8 $end
$var wire 1 &# AND9 $end
$var wire 1 $ clk $end
$var wire 3 '# r [2:0] $end
$var wire 1 (# r0XORAND2 $end
$var wire 1 )# r0XORAND4 $end
$var wire 1 *# r1XORAND3 $end
$var wire 1 +# r1XORAND7 $end
$var wire 1 ,# r2XORAND6 $end
$var wire 1 -# r2XORAND8 $end
$var wire 3 .# x [2:0] $end
$var wire 3 /# y [2:0] $end
$var wire 3 0# z [2:0] $end
$var wire 9 1# DFFout [9:1] $end
$scope module D1 $end
$var wire 1 $ clk $end
$var wire 1 |" in $end
$var parameter 32 2# N $end
$var reg 1 3# out $end
$upscope $end
$scope module D2 $end
$var wire 1 $ clk $end
$var wire 1 (# in $end
$var parameter 32 4# N $end
$var reg 1 5# out $end
$upscope $end
$scope module D3 $end
$var wire 1 $ clk $end
$var wire 1 *# in $end
$var parameter 32 6# N $end
$var reg 1 7# out $end
$upscope $end
$scope module D4 $end
$var wire 1 $ clk $end
$var wire 1 )# in $end
$var parameter 32 8# N $end
$var reg 1 9# out $end
$upscope $end
$scope module D5 $end
$var wire 1 $ clk $end
$var wire 1 "# in $end
$var parameter 32 :# N $end
$var reg 1 ;# out $end
$upscope $end
$scope module D6 $end
$var wire 1 $ clk $end
$var wire 1 ,# in $end
$var parameter 32 <# N $end
$var reg 1 =# out $end
$upscope $end
$scope module D7 $end
$var wire 1 $ clk $end
$var wire 1 +# in $end
$var parameter 32 ># N $end
$var reg 1 ?# out $end
$upscope $end
$scope module D8 $end
$var wire 1 $ clk $end
$var wire 1 -# in $end
$var parameter 32 @# N $end
$var reg 1 A# out $end
$upscope $end
$scope module D9 $end
$var wire 1 $ clk $end
$var wire 1 &# in $end
$var parameter 32 B# N $end
$var reg 1 C# out $end
$upscope $end
$upscope $end
$scope module G6 $end
$var wire 1 D# AND1 $end
$var wire 1 E# AND2 $end
$var wire 1 F# AND3 $end
$var wire 1 G# AND4 $end
$var wire 1 H# AND5 $end
$var wire 1 I# AND6 $end
$var wire 1 J# AND7 $end
$var wire 1 K# AND8 $end
$var wire 1 L# AND9 $end
$var wire 1 $ clk $end
$var wire 3 M# r [2:0] $end
$var wire 1 N# r0XORAND2 $end
$var wire 1 O# r0XORAND4 $end
$var wire 1 P# r1XORAND3 $end
$var wire 1 Q# r1XORAND7 $end
$var wire 1 R# r2XORAND6 $end
$var wire 1 S# r2XORAND8 $end
$var wire 3 T# x [2:0] $end
$var wire 3 U# y [2:0] $end
$var wire 3 V# z [2:0] $end
$var wire 9 W# DFFout [9:1] $end
$scope module D1 $end
$var wire 1 $ clk $end
$var wire 1 D# in $end
$var parameter 32 X# N $end
$var reg 1 Y# out $end
$upscope $end
$scope module D2 $end
$var wire 1 $ clk $end
$var wire 1 N# in $end
$var parameter 32 Z# N $end
$var reg 1 [# out $end
$upscope $end
$scope module D3 $end
$var wire 1 $ clk $end
$var wire 1 P# in $end
$var parameter 32 \# N $end
$var reg 1 ]# out $end
$upscope $end
$scope module D4 $end
$var wire 1 $ clk $end
$var wire 1 O# in $end
$var parameter 32 ^# N $end
$var reg 1 _# out $end
$upscope $end
$scope module D5 $end
$var wire 1 $ clk $end
$var wire 1 H# in $end
$var parameter 32 `# N $end
$var reg 1 a# out $end
$upscope $end
$scope module D6 $end
$var wire 1 $ clk $end
$var wire 1 R# in $end
$var parameter 32 b# N $end
$var reg 1 c# out $end
$upscope $end
$scope module D7 $end
$var wire 1 $ clk $end
$var wire 1 Q# in $end
$var parameter 32 d# N $end
$var reg 1 e# out $end
$upscope $end
$scope module D8 $end
$var wire 1 $ clk $end
$var wire 1 S# in $end
$var parameter 32 f# N $end
$var reg 1 g# out $end
$upscope $end
$scope module D9 $end
$var wire 1 $ clk $end
$var wire 1 L# in $end
$var parameter 32 h# N $end
$var reg 1 i# out $end
$upscope $end
$upscope $end
$scope module G7 $end
$var wire 1 j# AND1 $end
$var wire 1 k# AND2 $end
$var wire 1 l# AND3 $end
$var wire 1 m# AND4 $end
$var wire 1 n# AND5 $end
$var wire 1 o# AND6 $end
$var wire 1 p# AND7 $end
$var wire 1 q# AND8 $end
$var wire 1 r# AND9 $end
$var wire 1 $ clk $end
$var wire 3 s# r [2:0] $end
$var wire 1 t# r0XORAND2 $end
$var wire 1 u# r0XORAND4 $end
$var wire 1 v# r1XORAND3 $end
$var wire 1 w# r1XORAND7 $end
$var wire 1 x# r2XORAND6 $end
$var wire 1 y# r2XORAND8 $end
$var wire 3 z# x [2:0] $end
$var wire 3 {# y [2:0] $end
$var wire 3 |# z [2:0] $end
$var wire 9 }# DFFout [9:1] $end
$scope module D1 $end
$var wire 1 $ clk $end
$var wire 1 j# in $end
$var parameter 32 ~# N $end
$var reg 1 !$ out $end
$upscope $end
$scope module D2 $end
$var wire 1 $ clk $end
$var wire 1 t# in $end
$var parameter 32 "$ N $end
$var reg 1 #$ out $end
$upscope $end
$scope module D3 $end
$var wire 1 $ clk $end
$var wire 1 v# in $end
$var parameter 32 $$ N $end
$var reg 1 %$ out $end
$upscope $end
$scope module D4 $end
$var wire 1 $ clk $end
$var wire 1 u# in $end
$var parameter 32 &$ N $end
$var reg 1 '$ out $end
$upscope $end
$scope module D5 $end
$var wire 1 $ clk $end
$var wire 1 n# in $end
$var parameter 32 ($ N $end
$var reg 1 )$ out $end
$upscope $end
$scope module D6 $end
$var wire 1 $ clk $end
$var wire 1 x# in $end
$var parameter 32 *$ N $end
$var reg 1 +$ out $end
$upscope $end
$scope module D7 $end
$var wire 1 $ clk $end
$var wire 1 w# in $end
$var parameter 32 ,$ N $end
$var reg 1 -$ out $end
$upscope $end
$scope module D8 $end
$var wire 1 $ clk $end
$var wire 1 y# in $end
$var parameter 32 .$ N $end
$var reg 1 /$ out $end
$upscope $end
$scope module D9 $end
$var wire 1 $ clk $end
$var wire 1 r# in $end
$var parameter 32 0$ N $end
$var reg 1 1$ out $end
$upscope $end
$upscope $end
$scope module for_r52 $end
$var wire 1 $ clk $end
$var wire 1 2$ in $end
$var parameter 32 3$ N $end
$var reg 1 4$ out $end
$upscope $end
$scope module for_r62 $end
$var wire 1 $ clk $end
$var wire 1 5$ in $end
$var parameter 32 6$ N $end
$var reg 1 7$ out $end
$upscope $end
$scope module for_r70 $end
$var wire 1 $ clk $end
$var wire 1 8$ in $end
$var parameter 32 9$ N $end
$var reg 1 :$ out $end
$upscope $end
$scope module for_r71 $end
$var wire 1 $ clk $end
$var wire 1 ;$ in $end
$var parameter 32 <$ N $end
$var reg 1 =$ out $end
$upscope $end
$upscope $end
$upscope $end
$enddefinitions $end
$comment Show the parameter values. $end
$dumpall
b1 <$
b1 9$
b1 6$
b1 3$
b1 0$
b1 .$
b1 ,$
b1 *$
b1 ($
b1 &$
b1 $$
b1 "$
b1 ~#
b1 h#
b1 f#
b1 d#
b1 b#
b1 `#
b1 ^#
b1 \#
b1 Z#
b1 X#
b1 B#
b1 @#
b1 >#
b1 <#
b1 :#
b1 8#
b1 6#
b1 4#
b1 2#
b1 z"
b1 x"
b1 v"
b1 t"
b1 r"
b1 p"
b1 n"
b1 l"
b1 j"
b1 T"
b1 R"
b1 P"
b1 N"
b1 L"
b1 J"
b1 H"
b1 F"
b1 D"
b1 ."
b1 ,"
b1 *"
b1 ("
b1 &"
b1 $"
b1 ""
b1 ~
b1 |
b1 f
b1 d
b1 b
b1 `
b1 ^
b1 \
b1 Z
b1 X
b1 V
$end
#0
$dumpvars
x=$
0;$
x:$
08$
x7$
05$
x4$
12$
x1$
x/$
x-$
x+$
x)$
x'$
x%$
x#$
x!$
bx }#
bx |#
bx {#
bx z#
xy#
xx#
xw#
xv#
xu#
xt#
b1xx s#
xr#
xq#
xp#
xo#
xn#
xm#
xl#
xk#
xj#
xi#
xg#
xe#
xc#
xa#
x_#
x]#
x[#
xY#
bx W#
bx V#
bx U#
bx T#
xS#
xR#
xQ#
xP#
xO#
xN#
bx00 M#
xL#
xK#
xJ#
xI#
xH#
xG#
xF#
xE#
xD#
xC#
xA#
x?#
x=#
x;#
x9#
x7#
x5#
x3#
bx 1#
bx 0#
bx /#
bx .#
x-#
x,#
x+#
x*#
x)#
x(#
bx10 '#
x&#
x%#
x$#
x##
x"#
x!#
x~"
x}"
x|"
x{"
xy"
xw"
xu"
xs"
xq"
xo"
xm"
xk"
bx i"
bx h"
b11 g"
b101 f"
1e"
0d"
0c"
1b"
0a"
1`"
b10 _"
0^"
1]"
1\"
0["
0Z"
0Y"
0X"
1W"
1V"
xU"
xS"
xQ"
xO"
xM"
xK"
xI"
xG"
xE"
bx C"
bx B"
b10 A"
b1 @"
1?"
1>"
0="
0<"
0;"
1:"
b100 9"
08"
07"
06"
05"
04"
03"
02"
11"
00"
x/"
x-"
x+"
x)"
x'"
x%"
x#"
x!"
x}
bx {
bx z
b1 y
b100 x
1w
1v
1u
0t
0s
0r
b100 q
0p
0o
1n
0m
0l
0k
0j
0i
0h
xg
xe
xc
xa
x_
x]
x[
xY
xW
bx U
bx T
b111 S
b110 R
0Q
0P
1O
0N
1M
0L
b100 K
1J
1I
1H
1G
1F
1E
0D
0C
0B
b110 A
b100 @
b1 ?
b101 >
b111 =
b1 <
b10 ;
b11 :
bx 9
b100 8
b100 7
b100 6
b10 5
bx10 4
bx00 3
b1xx 2
bx 1
bx 0
bx /
bx .
bx -
bx ,
b1001011010001101000111 +
b1010100100100 *
bx )
b1001011010001101000111 (
bx '
bx &
b1010100100100 %
0$
bx #
x"
b11000001 !
$end
#5000
0)#
1+#
0(#
1-#
1*#
1,#
1O#
1Q#
0N#
0S#
1P#
1R#
0|"
0!#
0$#
0}"
0"#
0%#
0~"
0##
0&#
1D#
1G#
1J#
0E#
0H#
0K#
1F#
1I#
1L#
b0 1
b0 T
b0 .#
b10 0
b10 z
b10 /#
b111 /
b111 B"
b111 T#
b101 .
b101 h"
b101 U#
b110 4
b110 '#
14$
b0 3
b0 M#
07$
0:$
b100 2
b100 s#
0=$
0W
0Y
0[
1]
1_
0a
1c
0e
b101011000 U
1g
0}
0!"
0#"
0%"
0'"
1)"
1+"
1-"
b11100000 {
0/"
0E"
1G"
0I"
0K"
0M"
1O"
0Q"
1S"
b10100010 C"
0U"
1k"
1m"
1o"
0q"
0s"
0u"
0w"
1y"
b10000111 i"
0{"
1$
#10000
1N
0O
1r
1D
0E
0H
0u
1i
0:"
0V"
1N#
0O#
0F
0I
0n
12"
01"
0W"
0]"
1L
1M
1P
0Q
0v
0w
1;$
0<"
0>"
1="
0?"
18$
1`"
1a"
1d"
1e"
b0 !
b111 A
b111 R
b100 >
b100 f"
b1 3
b1 M#
b100 =
b100 S
b1 @
b1 x
b10 <
b10 y
b100 ;
b100 A"
b1 :
b1 g"
b1 8
b1 K
b0 7
b0 q
b10 6
b10 9"
b111 5
b111 _"
0$
b11010100000100101100011 (
b11010100000100101100011 +
b1101010 )
b1100011 '
b1001 &
b1111010000001 %
b1111010000001 *
#15000
0Q#
0P#
0+#
1w#
1y#
0u#
1x#
0t#
1v#
0J#
1O#
0R#
0D#
0F#
1$#
0p#
0q#
0r#
1m#
1n#
0o#
1j#
1k#
0l#
0G#
0I#
b100 .
b100 h"
b100 U#
b100 1
b100 T
b100 .#
b11 ,
b11 V#
b11 {#
b11 -
b11 0#
b11 z#
b100 /
b100 B"
b100 T#
b1 0
b1 z
b1 /#
1i#
0g#
1e#
1c#
0a#
0_#
1]#
1[#
b101100111 W#
1Y#
0C#
1A#
1?#
1=#
0;#
09#
17#
05#
b11100100 1#
03#
1u"
1q"
b10101110 i"
0k"
0S"
1Q"
0O"
b1000000 C"
0G"
0-"
0+"
0)"
b10 {
1!"
0c
1a
0_
1[
b100101110 U
1Y
1=$
b111 2
b111 s#
1:$
1$
#20000
0N
1w
0i
0t
1;"
0*#
1+#
0D
0G
0J
1o
0j
1p
13"
02"
0\"
15$
1P
1Q
08$
1r
1s
02$
0;$
0<"
1>"
0="
1?"
0b"
0c"
b11001011 !
b110 A
b110 R
b100 4
b100 '#
b0 =
b0 S
b100 @
b100 x
b110 <
b110 y
b10 ?
b10 @"
b1 ;
b1 A"
b0 >
b0 f"
b110 :
b110 g"
b101 8
b101 K
b1 7
b1 q
b100 6
b100 9"
b101 5
b101 _"
0$
b110111111001100110001101 (
b110111111001100110001101 +
b1101100001101 %
b1101100001101 *
#25000
0x#
0"
1(#
1%#
1+#
0*#
1O#
1Q#
1o#
1|"
1}"
1$#
0~"
0I#
0G#
1J#
0j#
1m#
0k#
1n#
b0 #
b0 9
b0 |#
0,#
1-#
1R#
1S#
0v#
0w#
0t#
1u#
b101 1
b101 T
b101 .#
b11 0
b11 z
b11 /#
b100 /
b100 B"
b100 T#
b101 .
b101 h"
b101 U#
b10 -
b10 0#
b10 z#
b111 ,
b111 V#
b111 {#
b0 4
b0 '#
04$
b101 3
b101 M#
17$
0:$
b100 2
b100 s#
0=$
0[
1e
b10101010 U
0g
1%"
1-"
b110001010 {
1/"
1K"
1O"
0Q"
b10101000 C"
1S"
b10101010 i"
0o"
b11100000 1#
07#
0Y#
0]#
1_#
0c#
b100001010 W#
0e#
1!$
0#$
1%$
0'$
1)$
1+$
1-$
1/$
b11110101 }#
01$
1$
#30000
03"
1V"
0(#
1)#
1*#
0+#
0p
0o
1Y"
05$
0r
0s
1v
1w
1:"
1;"
0>"
0?"
0`"
1b"
1a"
0d"
1c"
0e"
1x#
0y#
b1110111 !
b0 ;
b0 A"
b11 4
b11 '#
b0 A
b0 R
b110 =
b110 S
b0 @
b0 x
b1 <
b1 y
b110 ?
b110 @"
b11 >
b11 f"
b1 :
b1 g"
b100 7
b100 q
b1 6
b1 9"
b10 5
b10 _"
b0 2
b0 s#
0$
b1101110101001000010010 (
b1101110101001000010010 +
b10001100101 %
b10001100101 *
#35000
1"
1w#
1P#
1+#
1p#
1r#
0N#
0Q#
0L#
1F#
0*#
0|"
0$#
0n#
1E#
0J#
1H#
1I#
1~"
1&#
b10 #
b10 9
b10 |#
b110 -
b110 0#
b110 z#
b101 ,
b101 V#
b101 {#
b110 .
b110 h"
b110 U#
b11 /
b11 B"
b11 T#
b110 0
b110 z
b110 /#
1R#
0S#
0/$
0-$
1'$
0%$
b111000 }#
0!$
1g#
1e#
b111101010 W#
1c#
0?#
0=#
19#
17#
b10001101 1#
13#
0y"
1w"
0u"
1o"
0m"
b1001101 i"
1k"
0S"
0O"
b1010 C"
1G"
0/"
1)"
0%"
b10100000 {
0!"
b1 3
b1 M#
07$
1$
